generate_password52/__init__.py
generate_password52/password.py
generate_password52-0.3.dist-info/METADATA
generate_password52-0.3.dist-info/WHEEL
generate_password52-0.3.dist-info/licenses/LICENSE
generate_password52-0.3.dist-info/RECORD
