Metadata-Version: 2.4
Name: generate_password52
Version: 0.3
Summary: bla bla bla
Author-email: levchik <levdobriy2012@mail.ru>
License-File: LICENSE
Classifier: License :: OSI Approved :: MIT License
Classifier: Operating System :: OS Independent
Classifier: Programming Language :: Python :: 3
Requires-Python: >=3.10.0
